jinja2_time/__init__.py
jinja2_time/jinja2_time.py
jinja2_time-0.1.0.dist-info/DESCRIPTION.rst
jinja2_time-0.1.0.dist-info/METADATA
jinja2_time-0.1.0.dist-info/metadata.json
jinja2_time-0.1.0.dist-info/RECORD
jinja2_time-0.1.0.dist-info/top_level.txt
jinja2_time-0.1.0.dist-info/WHEEL
