Metadata-Version: 2.0
Name: jinja2-time
Version: 0.1.0
Summary: Jinja2 Extension for Dates and Times
Home-page: https://github.com/hackebrot/jinja2-time
Author: Raphael Pierzina
Author-email: raphael@hackebrot.de
License: MIT
Keywords: jinja2,extension,time
Platform: UNKNOWN
Classifier: Development Status :: 3 - Alpha
Classifier: Intended Audience :: Developers
Classifier: License :: OSI Approved :: MIT License
Classifier: Natural Language :: English
Classifier: Operating System :: OS Independent
Classifier: Programming Language :: Python :: 2
Classifier: Programming Language :: Python :: 2.7
Classifier: Programming Language :: Python :: 3
Classifier: Programming Language :: Python :: 3.3
Classifier: Programming Language :: Python :: 3.4
Classifier: Programming Language :: Python :: 3.5
Classifier: Programming Language :: Python :: Implementation :: CPython
Classifier: Programming Language :: Python :: Implementation :: PyPy
Classifier: Programming Language :: Python
Requires-Dist: jinja2
Requires-Dist: arrow
